moshmosh/__init__.py
moshmosh/ast_compat.py
moshmosh/ctx_fix.py
moshmosh/extension.py
moshmosh/extension_register.py
moshmosh/rewrite_helper.py
moshmosh/extensions/__init__.py
moshmosh/extensions/pipelines.py
moshmosh/extensions/quick_lambdas.py
moshmosh/extensions/scoped_operators.py
moshmosh/extensions/template_python.py
moshmosh/extensions/pattern_matching/__init__.py
moshmosh/extensions/pattern_matching/core.py
moshmosh/extensions/pattern_matching/main.py
moshmosh/extensions/pattern_matching/runtime.py
tests/__init__.py
tests/__main__.py
tests/ast_shape.py
tests/asts.py
tests/complex_match.py
tests/complex_match_py34.py
tests/list_view.py
tests/match.py
tests/pipelines.py
tests/py35_unparse.py
tests/quick_lambdas.py
tests/scoped_operators.py
tests/template_python.py
tests/test_all.py
moshmosh_base-0.2.dist-info/LICENSE
moshmosh_base-0.2.dist-info/METADATA
moshmosh_base-0.2.dist-info/WHEEL
moshmosh_base-0.2.dist-info/entry_points.txt
moshmosh_base-0.2.dist-info/top_level.txt
moshmosh_base-0.2.dist-info/RECORD
