Metadata-Version: 2.1
Name: moshmosh-base
Version: 0.2
Summary: advanced syntax&semantics extension system for Python
Home-page: https://github.com/thautwarm/moshmosh
Author: thautwarm
Author-email: twshere@outlook.com
License: mit
Keywords: syntax,semantics,extension,macro,pattern matching
Platform: any
Classifier: Programming Language :: Python :: 3.5
Classifier: Programming Language :: Python :: 3.6
Classifier: Programming Language :: Python :: 3.7
Classifier: Programming Language :: Python :: Implementation :: CPython
Requires-Python: >=3.5
Requires-Dist: toolz
